setup.py
alauda/__init__.py
alauda/alauda.py
alauda/apibase.py
alauda/application.py
alauda/build.py
alauda/region.py
alauda/repository.py
alauda/service.py
just4alauda.egg-info/PKG-INFO
just4alauda.egg-info/SOURCES.txt
just4alauda.egg-info/dependency_links.txt
just4alauda.egg-info/requires.txt
just4alauda.egg-info/top_level.txt