Metadata-Version: 1.1
Name: just4alauda
Version: 0.2.12
Summary: An simple python API for alauda.cn and alauda.io
Home-page: https://github.com/Just4test/Alauda
Author: Just4test
Author-email: myservice@just4test.net
License: wtfpl
Keywords: alauda,api
Platform: any
Classifier: Development Status :: 3 - Alpha
Classifier: Programming Language :: Python :: 3 :: Only
